{
  "generator-jhipster": {
    "applicationType": "monolith",
    "authenticationType": "jwt",
    "baseName": "OpenBankDemo",
    "blueprints": [],
    "buildTool": "maven",
    "cacheProvider": "caffeine",
    "clientFramework": "react",
    "clientPackageManager": "npm",
    "creationTimestamp": 1728141327481,
    "databaseType": "sql",
    "devDatabaseType": "mysql",
    "devServerPort": 9060,
    "enableHibernateCache": true,
    "enableSwaggerCodegen": "true",
    "enableTranslation": true,
    "entities": [],
    "gitCompany": "",
    "jhiPrefix": "jhi",
    "jhipsterVersion": "8.7.1",
    "jwtSecretKey": "YmVlMmM5MGNlZmU3NzkyMDVhZWVlNGE2MDgwMWM2MjU0NTFkOGVmY2ZiYWI4YjE2ZTFmMDNmYjdiNDQzNWYwNmZkYjEzMzRlZmY2OWE5MDhiNzE1Yjc5ODkyMDA5NzE0ZWFhZGY5NDcwODQxYTFlMDQzNjM2NTkxZWJhZTdhNmE=",
    "languages": ["en"],
    "messageBroker": false,
    "nativeLanguage": "en",
    "packageFolder": "io/openbak/demo",
    "packageName": "io.openbak.demo",
    "prodDatabaseType": "mysql",
    "searchEngine": false,
    "serverPort": 8080,
    "serviceDiscoveryType": false,
    "testFrameworks": [],
    "useSass": true,
    "websocket": false,
    "withAdminUi": true
  },
  "git-company": "paulozagaloneves",
  "git-provider": "GitHub",
  "repository-name": "open-bank-demo"
}
